umling/__init__.py
umling/pymol.py
umling-0.1.8.dist-info/METADATA
umling-0.1.8.dist-info/WHEEL
umling-0.1.8.dist-info/licenses/LICENSE
umling-0.1.8.dist-info/RECORD
