Metadata-Version: 2.4
Name: umling
Version: 0.1.8
Summary: Project umling
Project-URL: Homepage, https://github.com/abney/umling
Project-URL: Documentation, https://umling.readthedocs.io/
Project-URL: Bug Tracker, https://github.com/abney/umling/issues
Author-email: Steven Abney <abney@umich.edu>
License-Expression: LicenseRef-University-of-Michigan-License
License-File: LICENSE
Classifier: License :: Other/Proprietary License
Classifier: Operating System :: OS Independent
Classifier: Programming Language :: Python :: 3
Requires-Python: >=3.7
Requires-Dist: pyfoma
